httpSigRc.py
httpSignature.py
httpie_signature.py
httpie_signature-0.0.1.dist-info/LICENSE
httpie_signature-0.0.1.dist-info/METADATA
httpie_signature-0.0.1.dist-info/WHEEL
httpie_signature-0.0.1.dist-info/entry_points.txt
httpie_signature-0.0.1.dist-info/top_level.txt
httpie_signature-0.0.1.dist-info/RECORD
