Metadata-Version: 2.1
Name: httpie-signature
Version: 0.0.1
Summary: Http Signature Authentication plugin for HTTPie.
Home-page: https://github.com/rymccarter721/httpie-signature
Download-URL: https://github.com/rymccarter721/httpie-signature
Author: Ryan McCarter
Author-email: ryanmccarter721@gmail.com
License: MIT
Platform: UNKNOWN
Classifier: Development Status :: 3 - Alpha
Classifier: Intended Audience :: Developers
License-File: LICENSE
Requires-Dist: httpie
Requires-Dist: requests
